[
    {
        "slug": "sleep-mask",
        "name": "Alaska Bear Natural Silk Sleep Mask",
        "category": "bedroom",
        "description": "A sleep aid and eye relaxer, made of 100% top-quality 19mm Natural mulberry silk on BOTH sides. Only super-soft, super-smooth mulberry silk offers the breathable, cool relaxation of the soothing masks found at the world's premier spas.",
        "price": "13.99",
        "material": "Silk",
        "size": "12.7cm x 12.7cm",
        "weight": "17.01g",
        "image": "https://m.media-amazon.com/images/I/711yfrILKUL._AC_SL1500_.jpg",
        "link": "https://www.amazon.ca/-/fr/Alaska-Bear-sommeil-naturelle-bandeau/dp/B00GSO1D9O/ref=pd_vtp_h_pd_vtp_h_sccl_3/140-2237464-2324151?pd_rd_w=CvLer&content-id=amzn1.sym.54a077ab-41be-4d2b-b691-c4848b60dd3b&pf_rd_p=54a077ab-41be-4d2b-b691-c4848b60dd3b&pf_rd_r=AWGQXAG1D5CM3N5G0F79&pd_rd_wg=GEYPy&pd_rd_r=033c9bd4-e61f-46d1-a5c3-a5f030110541&pd_rd_i=B00GSO1D9O&psc=1",
        "height": 115,
        "width": 275
        
    },
    {
        "slug": "sheet-set",
        "name": "Queen Sheet Set",
        "category": "bedroom",
        "description": "Queen set includes a 90 x 102 inch flat sheet, 60 x 80 x 14 inch fitted sheet, and 2 pillowcases.Super soft and durable polyester microfiber (85 GSM) fabric offers all-season comfort and resists wrinkles and fading.",
        "price": "29.86",
        "material": "Polyester",
        "size": "Queen",
        "weight": "1.25kg",
        "image": "https://m.media-amazon.com/images/I/51vdF7fqxsL._AC_SL1500_.jpg",
        "link": "https://www.amazon.ca/-/fr/AmazonBasics-Parure-draps-en-microfibre/dp/B0154ASID6/?_encoding=UTF8&pd_rd_w=vV2CY&content-id=amzn1.sym.4c0a4723-ace2-4766-bab2-7b77118fd46c&pf_rd_p=4c0a4723-ace2-4766-bab2-7b77118fd46c&pf_rd_r=3GRGCBG4BB913CZDE7FG&pd_rd_wg=WcCk2&pd_rd_r=e7bd9954-57ce-4fdf-98e9-123d9d1b45bc&ref_=pd_gw_crs_zg_bs_2206275011&th=1&language=en_CA",
        "height": 155,
        "width": 275
    },
    {
        "slug": "sleep-pillows",
        "name": "Alternative Bed Pillows",
        "category": "bedroom",
        "description": "King-size bed pillow (2-pack) offers exceptional comfort; more plush than firm, this density is ideal for stomach and back sleepers.",
        "price": "67.82",
        "material": "Polyester",
        "size": "King",
        "weight": "2.6kg",
        "image": "https://m.media-amazon.com/images/I/51camcx6KGS._AC_SL1500_.jpg",
        "link": "https://www.amazon.ca/AmazonBasics-Down-Alternative-Bed-Pillows/dp/B0736YM33H?ref_=ast_sto_dp&th=1",
        "height": 169,
        "width": 275
    },
    {
        "slug": "laundry-basket",
        "name": "Foldable Laundry Basket Hamper",
        "category": "bedroom",
        "description": "Laundry hamper fits neatly into almost any closet space or bathroom for better organization.",
        "price": "24.87",
        "material": "Canvas",
        "size": "35.9cm x 58.5cm",
        "weight": "1.36kg",
        "image": "https://m.media-amazon.com/images/I/61oRVoZDB-L._AC_SL1500_.jpg",
        "link": "https://www.amazon.ca/AmazonBasics-AQ-NON005-Foldable-Laundry-Hamper/dp/B01IG6C0D4?ref_=ast_sto_dp&th=1&psc=1",
        "height": 275,
        "width": 188
    },
    {
        "slug": "travel-suitcase",
        "name": "Black Travel Luggage Suitcase",
        "category": "travel",
        "description": "24-inch hardside spinner check-in luggage—ideal for 3- to 5-day trips. Expandable for up to 15% additional packing capacity; solid, strong zippers; telescoping handle for comfortable maneuvering; securely mounted short handle.",
        "price": "146.33",
        "material": "ABS",
        "size": "45.1cm x 67.1cm",
        "weight": "4.25kg",
        "image": "https://m.media-amazon.com/images/I/91DJfOB6mHL._AC_SL1500_.jpg",
        "link": "https://www.amazon.ca/AmazonBasics-Hardside-Spinner-Luggage-24-inch/dp/B071NPGSRM?ref_=ast_sto_dp&th=1",
        "height": 275,
        "width": 159
    },
    {
        "slug": "duffel-bag",
        "name": "Travel Gym Duffel Bag",
        "category": "travel",
        "description": "Travel duffel bag for use as primary luggage, an extra just-in-case bag, for sports gear, and more.",
        "price": "39.91",
        "material": "Fabric",
        "size": "68.6cm x 39.4cm",
        "weight": "408.23g",
        "image": "https://m.media-amazon.com/images/I/81QGVZnoyYL._AC_SL1500_.jpg",
        "link": "https://www.amazon.ca/AmazonBasics-Packable-Travel-Duffel-27-inch/dp/B01J24HEE4?ref_=ast_sto_dp",
        "height": 181,
        "width": 275
    },
    {
        "slug": "camping-chair",
        "name": "Portable Camping Chair",
        "category": "outdoor",
        "description": "Padded camping chair (XL) with fully cushioned seat and back for comfort; sleek black color. Built-in beverage-cooler pouch (hangs from armrest) for up to 4 12-ounce cans.",
        "price": "102.40",
        "material": "Alloy Steel",
        "size": "96.5cm x 91.4cm",
        "weight": "3.9kg",
        "image": "https://m.media-amazon.com/images/I/91k6TAPTSJL._AC_SL1500_.jpg",
        "link": "https://www.amazon.ca/AmazonBasics-Camping-Chair-Cooler-Padded/dp/B074YR4LR1?ref_=ast_sto_dp&th=1",
        "height": 275,
        "width": 233
    },
    {
        "slug": "campfire-grill",
        "name": "Folding Campfire Grill",
        "category": "outdoor",
        "description": "Heavy-duty campfire grill for cooking over an open fire.",
        "price": "34.39",
        "material": "Alloy Steel",
        "size": "29.9cm x 46.9cm",
        "weight": "2.23kg",
        "image": "https://m.media-amazon.com/images/I/71ruUErO+zL._AC_SL1500_.jpg",
        "link": "https://www.amazon.ca/AmazonBasics-Heavy-Folding-Campfire-Medium/dp/B074N1W4G8?ref_=ast_sto_dp&th=1&psc=1",
        "height": 133,
        "width": 275
    },
    {
        "slug": "bike-lock",
        "name": "Bike Cable Lock",
        "category": "outdoor",
        "description": "Black finish.Note: Measure your door's backset, cross bore and thickness to ensure you find the right fit.",
        "price": "17.31",
        "material": "Plastic",
        "size": "17.8cm x 10.2cm",
        "weight": "276.69g",
        "image": "https://m.media-amazon.com/images/I/81LqEmzPdzL._AC_SL1500_.jpg",
        "link": "https://www.amazon.ca/AmazonBasics-Combination-Cable-Black-1-Pack/dp/B07T3F6JST?ref_=ast_sto_dp&th=1&psc=1",
        "height": 275,
        "width": 268
    },
    {
        "slug": "backpack",
        "name": "Ultralight Portable Day Pack",
        "category": "outdoor",
        "description": "Ultra-light packable daypack with 25-liter capacity and 2-way zipper for secure closure.",
        "price": "20.13",
        "material": "Polyester",
        "size": "44.45cm x 29.21cm",
        "weight": "158.76g",
        "image": "https://m.media-amazon.com/images/I/91st5RiMpGL._AC_SL1500_.jpg",
        "link": "https://www.amazon.ca/AmazonBasics-Ultralight-Packable-Day-Pack/dp/B01AIVT6NM?ref_=ast_sto_dp&th=1",
        "height": 275,
        "width": 183
    },
    {
        "slug": "livingroom-chair",
        "name": "Rivet Bayard Livingroom Chair",
        "category": "furniture",
        "description": "This living room chair is a stylish way to add extra seating wherever you need it. Leather upholstery and tapered legs combine modern design elements with a graceful silhouette. Sit in comfort supported by foam-padded cushions, a solid wood frame and gently sloping armrests.",
        "price": "1,116.87",
        "material": "Leather",
        "size": "85cm x 83cm",
        "weight": "21kg",
        "image": "https://m.media-amazon.com/images/I/81F6XdxTUgL._AC_SL1500_.jpg",
        "link": "https://www.amazon.ca/Amazon-Brand-Contemporary-Leather-Armrests/dp/B082QDDJV9?ref_=ast_sto_dp&th=1&psc=1",
        "height": 256,
        "width": 275
    },
    {
        "slug": "coffee-table",
        "name": "Lift-Top Storage Coffee Table",
        "category": "furniture",
        "description": "Coffee table with top that lifts to create a sturdy, raised work surface; ideal for a living room, family room, or office.",
        "price": "244.77",
        "material": "Wood",
        "size": "48.3cm x 101.6cm",
        "weight": "17.69kg",
        "image": "https://m.media-amazon.com/images/I/618HEDWXJQL._AC_SL1500_.jpg",
        "link": "https://www.amazon.ca/AmazonBasics-Lift-Top-Storage-Coffee-Table/dp/B07J29V51Q?ref_=ast_sto_dp&th=1&psc=1",
        "height": 162,
        "width": 275
    },
    {
        "slug": "storage-bench",
        "name": "Upholstered Storage Ottoman Bench",
        "category": "furniture",
        "description": "Bench-style ottoman offers extra storage and seating space; great for an entryway, living room, family room, or bedroom.",
        "price": "231.23",
        "material": "Wood",
        "size": "16.5cm x 35.5cm",
        "weight": "10.43kg",
        "image": "https://m.media-amazon.com/images/I/81gnyhw-npL._AC_SL1500_.jpg",
        "link": "https://www.amazon.ca/AmazonBasics-Storage-Bench-Ottoman-Beige/dp/B0871DCPSZ?ref_=ast_sto_dp&th=1&psc=1",
        "height": 156,
        "width": 275
    },
    {
        "slug": "wall-pockets",
        "name": "Expandable Wall Pockets",
        "category": "office",
        "description": "Expandable wall pocket (3-pack) creates instant additional storage space, freeing up desktop and tabletop surfaces.",
        "price": "19.46",
        "material": "Plastic",
        "size": "33.2cm x 30.3",
        "weight": "0.19kg",
        "image": "https://m.media-amazon.com/images/I/61-JfzD6nyL._AC_SL1500_.jpg",
        "link": "https://www.amazon.ca/Amazonbasics-Expandable-Pockets-Letter-3-Pocket/dp/B07VWH29PB?ref_=ast_sto_dp&th=1",
        "height": 275,
        "width": 247
    },
    {
        "slug": "stereo-speaker",
        "name": "Water Resistant Outdoor Speaker",
        "category": "audio",
        "description": "9 watt bluetooth-compatible speaker for indoor and outdoor use. Water-resistant construction protects against moisture damage",
        "price": "46.57",
        "material": "N/A",
        "size": "N/A",
        "weight": "0.39kg",
        "image": "https://m.media-amazon.com/images/I/91Vhs3aNeEL._AC_SL1500_.jpg",
        "link": "https://www.amazon.ca/AmazonBasics-9-Watt-Bluetooth-Speaker-Resistant/dp/B07PH2HVGM?ref_=ast_sto_dp&th=1",
        "height": 118,
        "width": 275
    },
    {
        "slug": "wired-earbuds",
        "name": "Wired Earbuds with Microphone",
        "category": "audio",
        "description": "Black headphones with comfortable in-ear design and 3.5mm gold-plated plug",
        "price": "15.23",
        "material": "Plastic",
        "size": "130cm x 1.3cm",
        "weight": "12.02g",
        "image": "https://m.media-amazon.com/images/I/51xZdrJfCzL._AC_SL1500_.jpg",
        "link": "https://www.amazon.ca/AmazonBasics-Ear-Headphones-Mic-Black/dp/B07HH1QSLB?ref_=ast_sto_dp&th=1&psc=1",
        "height": 275,
        "width": 133
    }
]